[
    {
        "key": "ctrl+s",
        "command": "workbench.action.files.save",
        "when": "editorTextFocus"
    },
    {
        "key": "ctrl+a",
        "command": "editor.action.selectAll",
        "when": "editorTextFocus"
    },
    {
        "key": "ctrl+d",
        "command": "editor.action.addSelectionToNextFindMatch",
        "when": "editorTextFocus"
    },
    {
        "key": "ctrl+c",
        "command": "editor.action.clipboardCopyAction",
        "when": "editorTextFocus"
    },
    {
        "key": "ctrl+x",
        "command": "editor.action.clipboardCutAction",
        "when": "editorTextFocus"
    },
    {
        "key": "ctrl+v",
        "command": "editor.action.clipboardPasteAction",
        "when": "editorTextFocus"
    },
    {
        "key": "alt+s",
        "command": "workbench.action.files.save",
        "when": "editorTextFocus"
    },
    {
        "key": "alt+a",
        "command": "editor.action.selectAll",
        "when": "editorTextFocus"
    },
    {
        "key": "alt+d",
        "command": "editor.action.duplicateSelection",
        "when": "editorTextFocus"
    },
    {
        "key": "alt+c",
        "command": "editor.action.clipboardCopyAction",
        "when": "editorTextFocus"
    },
    {
        "key": "alt+x",
        "command": "editor.action.clipboardCutAction",
        "when": "editorTextFocus"
    },
    {
        "key": "alt+v",
        "command": "editor.action.clipboardPasteAction",
        "when": "editorTextFocus"
    }
]
